LICENSE
README.md
pyproject.toml
setup.cfg
setup.py
ibind/__init__.py
ibind/var.py
ibind.egg-info/PKG-INFO
ibind.egg-info/SOURCES.txt
ibind.egg-info/dependency_links.txt
ibind.egg-info/requires.txt
ibind.egg-info/top_level.txt
ibind/base/__init__.py
ibind/base/queue_controller.py
ibind/base/rest_client.py
ibind/base/subscription_controller.py
ibind/base/ws_client.py
ibind/client/__init__.py
ibind/client/ibkr_client.py
ibind/client/ibkr_definitions.py
ibind/client/ibkr_utils.py
ibind/client/ibkr_ws_client.py
ibind/client/ibkr_client_mixins/__init__.py
ibind/client/ibkr_client_mixins/accounts_mixin.py
ibind/client/ibkr_client_mixins/contract_mixin.py
ibind/client/ibkr_client_mixins/marketdata_mixin.py
ibind/client/ibkr_client_mixins/order_mixin.py
ibind/client/ibkr_client_mixins/portfolio_mixin.py
ibind/client/ibkr_client_mixins/scanner_mixin.py
ibind/client/ibkr_client_mixins/session_mixin.py
ibind/client/ibkr_client_mixins/watchlist_mixin.py
ibind/oauth/__init__.py
ibind/oauth/oauth1a.py
ibind/support/__init__.py
ibind/support/errors.py
ibind/support/logs.py
ibind/support/py_utils.py
test/__init__.py
test/test_utils.py
test/integration/__init__.py
test/integration/base/__init__.py
test/integration/base/test_rest_client_i.py
test/integration/base/test_websocket_client_i.py
test/integration/base/websocketapp_mock.py
test/integration/client/__init__.py
test/integration/client/ibkr_responses.py
test/integration/client/test_ibkr_client_i.py
test/integration/client/test_ibkr_utils_i.py
test/integration/client/test_ibkr_ws_client_i.py
test/unit/__init__.py
test/unit/client/__init__.py
test/unit/client/test_ibkr_client_u.py
test/unit/support/__init__.py
test/unit/support/test_py_utils_u.py