Metadata-Version: 2.4
Name: ibind
Version: 0.1.19
Summary: IBind is a REST and WebSocket client library for Interactive Brokers Client Portal Web API.
Author-email: Voy Zan <voy1982@yahoo.co.uk>
Project-URL: Homepage, https://github.com/Voyz/ibind
Keywords: interactive brokers,rest api,python api,ibkr python api,ibkr web api,ib api,ibkr api,algo trading,algorithmic trading,quant,trading
Classifier: Development Status :: 4 - Beta
Classifier: Programming Language :: Python :: 3
Classifier: Programming Language :: Python :: 3.10
Classifier: Programming Language :: Python :: 3.11
Classifier: Programming Language :: Python :: 3.12
Classifier: Programming Language :: Python :: 3.13
Classifier: Operating System :: OS Independent
Classifier: Intended Audience :: Financial and Insurance Industry
Classifier: Topic :: Office/Business :: Financial :: Investment
Requires-Python: >=3.8
License-File: LICENSE
Requires-Dist: requests>=2.31
Requires-Dist: websocket-client>=1.7
Provides-Extra: oauth
Requires-Dist: pycryptodome>=3.21; extra == "oauth"
Requires-Dist: urllib3>=2.3; extra == "oauth"
Dynamic: license-file
